{
  "properties": {
    "name": {
      "title": "Name",
      "type": "string"
    },
    "address": {
      "title": "Address",
      "type": "string"
    },
    "description": {
      "anyOf": [
        {
          "type": "string"
        },
        {
          "type": "null"
        }
      ],
      "title": "Description"
    },
    "active": {
      "default": true,
      "title": "Active",
      "type": "boolean"
    }
  },
  "required": [
    "name",
    "address",
    "description"
  ],
  "title": "HouseholdBase",
  "type": "object"
}